signed_multiplier/multiplier.v
/*
Signed Multiplier using Booth's Algorithm.
Author: Subash Ganti
*/

module PIPO #(
    parameter SIZE = 8)
 (
    output reg [SIZE-1:0] data_out,
    input [SIZE-1:0] data_in,
    input ld,
    input clr,
    input clk
);
always@(posedge clk)
    begin
        if(clr) data_out<=0;
        else if (ld) data_out<=data_in;
    end
endmodule

module shiftreg(data_out, data_in, d_in, ld, sft, clr, clk);
    parameter SIZE = 8;
    output reg[SIZE-1:0] data_out;
    input [SIZE-1:0] data_in;
    input d_in, ld, sft, clr, clk;

    always@(posedge clk)
    begin
        if(clr) data_out<=0;
        else if(sft) data_out<={d_in,data_out[SIZE-1:1]};
        else if(ld) data_out<=data_in;
    end
endmodule

module counter(count, reset, down_count, clk);
    parameter SIZE = 8;
    output reg[SIZE-1:0] count;
    input reset,clk,down_count;
    
    always@(posedge clk)
    begin
        if(reset) count<=SIZE;
        else if(down_count)count <= count -1;
    end
endmodule

module addsub(S,A,B,ctrl);
    parameter SIZE = 8;
    output reg[SIZE-1:0] S;
    input [SIZE-1:0] A;
    input [SIZE-1:0] B;
    input [1:0] ctrl;

    always@(A,B,ctrl)
    begin
        case (ctrl)
            2'b00 : S = B;
            2'b01 : S = A + B;
            2'b10 : S = (~A) + B + 1;
            default: S = B;
        endcase
    end   
endmodule

module datapath(data_out, count, op_con, data_in, lda, ldb, lds, ldq, sftb, clr, addctrl,down_count, clk);
    parameter SIZE = 8;
    output [(2*SIZE)-1:0] data_out;
    output [SIZE-1:0] count;
    output [1:0] op_con; // operation codition
    input [SIZE-1:0] data_in;
    input lda,ldb,lds,ldq,sftb,clr,clk,down_count;
    input [1:0] addctrl;

    wire [SIZE-1:0] A,B,S,P;
    wire Q;
    wire clrA;

    PIPO #(.SIZE(SIZE)) A_reg(A,data_in,lda,clrA,clk);
    PIPO #(.SIZE(SIZE)) S_reg(S,{P[SIZE-1], P[SIZE-1:1]}, lds, clr, clk);
    PIPO #(.SIZE(1))    Q_reg(Q,B[0],ldq,clr,clk);
    shiftreg #(.SIZE(SIZE)) B_reg(B,data_in,P[0],ldb,sftb,clr,clk);
    counter #(.SIZE(SIZE)) C0(count, clr,down_count, clk);
    addsub #(.SIZE(SIZE))  A0(P, A, S, addctrl);
    
    assign clrA = 1'b0;
    assign op_con = {B[0], Q};
    assign data_out = {S,B};

endmodule

module controller(start, reset, clk, op_con, count, lda, ldb, lds, ldq, sftb, addctrl, clr, down_count, done);
    
    parameter SIZE = 8;

    input start,reset,clk;
    input [1:0] op_con;
    input [SIZE-1:0] count;
    output reg lda, ldb, lds, ldq, sftb, clr, done, down_count;
    output reg [1:0] addctrl;

    reg [2:0] state, next_state;
    parameter S0 = 3'b000, S1 = 3'b001, S2 = 3'b010, S3 = 3'b011, S4 = 3'b100;

    always@(posedge clk)
        state <= next_state;

    // Determinig next state.
    always@(state, start, reset, count)
        begin
            case (state)
                S0: begin if(reset) next_state = S0; else begin if(start) next_state = S1; else next_state = S0;end end
                S1: begin if(reset) next_state = S0; else next_state = S2; end
                S2: begin if(reset) next_state = S0; else next_state = S3; end
                S3: begin if(reset) next_state = S0; else begin if(count==0) next_state = S4; else next_state = S3; end end
                S4: begin if(reset) next_state = S0; else next_state = S4;end
                default: next_state = S0;
            endcase
        end

    // Determining outputs
   always@(state, start, count, op_con)
   begin
        case (state)
            S0: begin clr = 1; lda = 0; ldb = 0; lds = 0; ldq = 0; sftb = 0; addctrl = 0; down_count = 0; done = 0;end 
            S1: begin clr = 0; lda = 1; ldb = 0;end
            S2: begin lda = 0; ldb = 1;end
            S3: begin 
                if(count == 0) begin lda = 0; ldb = 0; sftb = 0; lds = 0; ldq = 0; clr = 0; down_count = 0; end
                else begin 
                    lda = 0; ldb = 0; lds = 1; ldq = 1; sftb = 1; clr = 0; down_count = 1;
                    case (op_con)
                        2'b00: addctrl = 2'b00;
                        2'b01: addctrl = 2'b01;
                        2'b10: addctrl = 2'b10;
                        2'b11: addctrl = 2'b00;
                        default: addctrl = 2'b00;
                    endcase 
                end
            end
            S4: begin lda = 0; ldb = 0; sftb = 0; lds =0; ldq = 0; clr = 0; done = 1; down_count = 0; end
            default: begin clr = 1; lda = 0; ldb = 0; lds = 0; ldq = 0; sftb = 0; addctrl = 0; done = 0; down_count = 0; end
        endcase
   end 
endmodule

module Multiplier(start, reset, clk, data_in, data_out, done);
    parameter SIZE = 8;
    input start, reset, clk;
    input [SIZE-1:0] data_in;
    output [(2*SIZE)-1:0] data_out; output done;

    wire lda, ldb, lds, ldq, sftb, clr, down_count;
    wire [1:0] addctrl, op_con;
    wire [SIZE-1:0] count;

    datapath #(.SIZE(SIZE)) d0(data_out, count, op_con, data_in, lda, ldb, lds, ldq, sftb, clr, addctrl,down_count, clk);
    controller #(.SIZE(SIZE)) c0(start, reset, clk, op_con, count, lda, ldb, lds, ldq, sftb, addctrl, clr,down_count, done);
endmodule

signed_multiplier/multiplier_tb.v
`include "multiplier.v"
`timescale 1ns/1ns

module multiplier_tb;

parameter SIZE = 8, tclk = 10;
reg start, reset, clk;
reg [SIZE-1:0] data_in;
wire [(2*SIZE)-1:0] data_out;
wire done;

integer n = 5;

byte arr1[4:0];
byte arr2[4:0];


initial
begin
arr1[0]= 14;
arr1[1]= 51;
arr1[2]=4;
arr1[3]= 11;
arr1[4]= 7;
arr2[0] = 8'b0000_0101;
arr2[1] = 8'b1111_1101;
arr2[2] = 8'b0000_1010;
arr2[3] = 8'b1111_1010;
arr2[4] = 8'b1110_1101;
end

Multiplier #(.SIZE(SIZE)) m0(start,reset,clk,data_in,data_out,done);

task generate_stimulus();
begin
    start <= 1'b0; reset <=1'b1; clk <= 1'b0;
    #(tclk) reset<=1'b0; start<=1'b1;
    #(tclk) start<=1'b0; data_in<=arr1[n];
    #(tclk) data_in<=arr2[n];
end
endtask

initial
begin
    $dumpfile("multiplier_tb.vcd");
    $dumpvars(0,multiplier_tb);
end

// generating the clock.
always #(tclk/2) clk = ~clk;

// Generating input stimulus
initial
begin
    n = n-1;
    generate_stimulus();
end

always@(posedge done)
begin
    if(n == 0) $finish;
    n = n-1;
    generate_stimulus();
end

initial
# 1000 $finish;

// Monitoring signals
initial
begin
    $monitor("time = %t, n=%d, A = %d, B =%b , S =%b, data_out=%b, count = %d, done=%b",$time,n, m0.d0.A, m0.d0.B, m0.d0.S,data_out,m0.count,done);
end
endmodule

signed_multiplier/multiplier_tb.vcd
$date
	Fri Oct 11 16:02:35 2024
$end
$version
	Icarus Verilog
$end
$timescale
	1ns
$end
$scope module multiplier_tb $end
$var wire 1 ! done $end
$var wire 16 " data_out [15:0] $end
$var reg 1 # clk $end
$var reg 8 $ data_in [7:0] $end
$var reg 1 % reset $end
$var reg 1 & start $end
$var integer 32 ' n [31:0] $end
$scope module m0 $end
$var wire 1 # clk $end
$var wire 8 ( data_in [7:0] $end
$var wire 1 % reset $end
$var wire 1 & start $end
$var wire 1 ) sftb $end
$var wire 2 * op_con [1:0] $end
$var wire 1 + lds $end
$var wire 1 , ldq $end
$var wire 1 - ldb $end
$var wire 1 . lda $end
$var wire 1 / down_count $end
$var wire 1 ! done $end
$var wire 16 0 data_out [15:0] $end
$var wire 8 1 count [7:0] $end
$var wire 1 2 clr $end
$var wire 2 3 addctrl [1:0] $end
$scope module c0 $end
$var wire 1 # clk $end
$var wire 1 % reset $end
$var wire 1 & start $end
$var wire 2 4 op_con [1:0] $end
$var wire 8 5 count [7:0] $end
$var reg 2 6 addctrl [1:0] $end
$var reg 1 2 clr $end
$var reg 1 ! done $end
$var reg 1 / down_count $end
$var reg 1 . lda $end
$var reg 1 - ldb $end
$var reg 1 , ldq $end
$var reg 1 + lds $end
$var reg 3 7 next_state [2:0] $end
$var reg 1 ) sftb $end
$var reg 3 8 state [2:0] $end
$upscope $end
$scope module d0 $end
$var wire 2 9 addctrl [1:0] $end
$var wire 1 # clk $end
$var wire 1 2 clr $end
$var wire 1 : clrA $end
$var wire 8 ; data_in [7:0] $end
$var wire 1 / down_count $end
$var wire 1 . lda $end
$var wire 1 - ldb $end
$var wire 1 , ldq $end
$var wire 1 + lds $end
$var wire 1 ) sftb $end
$var wire 2 < op_con [1:0] $end
$var wire 16 = data_out [15:0] $end
$var wire 8 > count [7:0] $end
$var wire 8 ? S [7:0] $end
$var wire 1 @ Q $end
$var wire 8 A P [7:0] $end
$var wire 8 B B [7:0] $end
$var wire 8 C A [7:0] $end
$scope module A0 $end
$var wire 2 D ctrl [1:0] $end
$var wire 8 E B [7:0] $end
$var wire 8 F A [7:0] $end
$var reg 8 G S [7:0] $end
$upscope $end
$scope module A_reg $end
$var wire 1 # clk $end
$var wire 1 : clr $end
$var wire 8 H data_in [7:0] $end
$var wire 1 . ld $end
$var reg 8 I data_out [7:0] $end
$upscope $end
$scope module B_reg $end
$var wire 1 # clk $end
$var wire 1 2 clr $end
$var wire 1 J d_in $end
$var wire 8 K data_in [7:0] $end
$var wire 1 - ld $end
$var wire 1 ) sft $end
$var reg 8 L data_out [7:0] $end
$upscope $end
$scope module C0 $end
$var wire 1 # clk $end
$var wire 1 / down_count $end
$var wire 1 2 reset $end
$var reg 8 M count [7:0] $end
$upscope $end
$scope module Q_reg $end
$var wire 1 # clk $end
$var wire 1 2 clr $end
$var wire 1 N data_in $end
$var wire 1 , ld $end
$var reg 1 @ data_out $end
$upscope $end
$scope module S_reg $end
$var wire 1 # clk $end
$var wire 1 2 clr $end
$var wire 8 O data_in [7:0] $end
$var wire 1 + ld $end
$var reg 8 P data_out [7:0] $end
$upscope $end
$upscope $end
$upscope $end
$scope task generate_stimulus $end
$upscope $end
$upscope $end
$enddefinitions $end
#0
$dumpvars
bx P
bx O
xN
bx M
bx L
bx K
xJ
bx I
bx H
bx G
bx F
bx E
b0 D
bx C
bx B
bx A
x@
bx ?
bx >
bx =
bx <
bx ;
0:
b0 9
bx 8
b0 7
b0 6
bx 5
bx 4
b0 3
12
bx 1
bx 0
0/
0.
0-
0,
0+
bx *
0)
bx (
b100 '
0&
1%
bx $
0#
bx "
0!
$end
#5
0J
b0 O
b0 A
b0 G
0N
b0 ?
b0 E
b0 P
b0 *
b0 4
b0 <
0@
b0 "
b0 0
b0 =
b0 B
b0 L
b1000 1
b1000 5
b1000 >
b1000 M
b0 8
1#
#10
b1 7
1&
0%
0#
#15
1.
02
b10 7
b1 8
1#
#20
b111 $
b111 (
b111 ;
b111 H
b111 K
0&
0#
#25
1-
0.
b11 7
b111 C
b111 F
b111 I
b10 8
1#
#30
b11101101 $
b11101101 (
b11101101 ;
b11101101 H
b11101101 K
0#
#35
1J
b11111100 O
b11111001 A
b11111001 G
b10 3
b10 6
b10 9
b10 D
1/
1)
1,
1+
0-
b10 *
b10 4
b10 <
1N
b11 8
b11101101 "
b11101101 0
b11101101 =
b11101101 B
b11101101 L
1#
#40
0#
#45
1J
b1 O
b11 A
b11 G
0N
b1 3
b1 6
b1 9
b1 D
b11111100 ?
b11111100 E
b11111100 P
b1 *
b1 4
b1 <
1@
b1111110011110110 "
b1111110011110110 0
b1111110011110110 =
b11110110 B
b11110110 L
b111 1
b111 5
b111 >
b111 M
1#
#50
0#
#55
0J
b11111101 O
1N
b10 3
b10 6
b10 9
b10 D
b11111010 A
b11111010 G
b110 1
b110 5
b110 >
b110 M
b11111011 B
b11111011 L
b10 *
b10 4
b10 <
0@
b111111011 "
b111111011 0
b111111011 =
b1 ?
b1 E
b1 P
1#
#60
0#
#65
1J
b11111110 O
b11111101 A
b11111101 G
b0 3
b0 6
b0 9
b0 D
b11111101 ?
b11111101 E
b11111101 P
b11 *
b11 4
b11 <
1@
b1111110101111101 "
b1111110101111101 0
b1111110101111101 =
b1111101 B
b1111101 L
b101 1
b101 5
b101 >
b101 M
1#
#70
0#
#75
1J
b10 O
b1 3
b1 6
b1 9
b1 D
b1 *
b1 4
b1 <
0N
b101 A
b101 G
b100 1
b100 5
b100 >
b100 M
b10111110 B
b10111110 L
b1111111010111110 "
b1111111010111110 0
b1111111010111110 =
b11111110 ?
b11111110 E
b11111110 P
1#
#80
0#
#85
1J
b11111101 O
b11111011 A
b11111011 G
1N
b10 3
b10 6
b10 9
b10 D
b10 ?
b10 E
b10 P
b10 *
b10 4
b10 <
0@
b1011011111 "
b1011011111 0
b1011011111 =
b11011111 B
b11011111 L
b11 1
b11 5
b11 >
b11 M
1#
#90
0#
#95
1J
b11111110 O
b0 3
b0 6
b0 9
b0 D
b11111101 A
b11111101 G
b10 1
b10 5
b10 >
b10 M
b11101111 B
b11101111 L
b11 *
b11 4
b11 <
1@
b1111110111101111 "
b1111110111101111 0
b1111110111101111 =
b11111101 ?
b11111101 E
b11111101 P
1#
#100
0#
#105
0J
b11111111 O
b11111110 A
b11111110 G
b11111110 ?
b11111110 E
b11111110 P
b1111111011110111 "
b1111111011110111 0
b1111111011110111 =
b11110111 B
b11110111 L
b1 1
b1 5
b1 >
b1 M
1#
#110
0#
#115
1J
0/
0,
0+
0)
b100 7
b11111111 A
b11111111 G
b0 1
b0 5
b0 >
b0 M
b1111011 B
b1111011 L
b1111111101111011 "
b1111111101111011 0
b1111111101111011 =
b11111111 ?
b11111111 E
b11111111 P
1#
#120
0#
#125
b0 7
1%
b11 '
1!
b100 8
0#
#130
0!
12
b0 8
1#
#135
b1 7
1&
0%
0#
#140
0J
b0 O
b0 A
b0 G
0N
1.
02
b10 7
b0 ?
b0 E
b0 P
b0 *
b0 4
b0 <
0@
b0 "
b0 0
b0 =
b0 B
b0 L
b1000 1
b1000 5
b1000 >
b1000 M
b1 8
1#
#145
b1011 $
b1011 (
b1011 ;
b1011 H
b1011 K
0&
0#
#150
1-
0.
b11 7
b10 8
b1011 C
b1011 F
b1011 I
1#
#155
b11111010 $
b11111010 (
b11111010 ;
b11111010 H
b11111010 K
0#
#160
1/
1)
1,
1+
0-
b11111010 "
b11111010 0
b11111010 =
b11111010 B
b11111010 L
b11 8
1#
#165
0#
#170
1J
b11111010 O
b11110101 A
b11110101 G
b10 3
b10 6
b10 9
b10 D
b10 *
b10 4
b10 <
1N
b111 1
b111 5
b111 >
b111 M
b1111101 "
b1111101 0
b1111101 =
b1111101 B
b1111101 L
1#
#175
0#
#180
1J
b10 O
b101 A
b101 G
0N
b1 3
b1 6
b1 9
b1 D
b11111010 ?
b11111010 E
b11111010 P
b1 *
b1 4
b1 <
1@
b1111101010111110 "
b1111101010111110 0
b1111101010111110 =
b10111110 B
b10111110 L
b110 1
b110 5
b110 >
b110 M
1#
#185
0#
#190
1J
b11111011 O
1N
b10 3
b10 6
b10 9
b10 D
b11110111 A
b11110111 G
b101 1
b101 5
b101 >
b101 M
b11011111 B
b11011111 L
b10 *
b10 4
b10 <
0@
b1011011111 "
b1011011111 0
b1011011111 =
b10 ?
b10 E
b10 P
1#
#195
0#
#200
b11111101 O
b11111011 A
b11111011 G
b0 3
b0 6
b0 9
b0 D
b11111011 ?
b11111011 E
b11111011 P
b11 *
b11 4
b11 <
1@
b1111101111101111 "
b1111101111101111 0
b1111101111101111 =
b11101111 B
b11101111 L
b100 1
b100 5
b100 >
b100 M
1#
#205
0#
#210
b11111110 O
b11111101 A
b11111101 G
b11 1
b11 5
b11 >
b11 M
b11110111 B
b11110111 L
b1111110111110111 "
b1111110111110111 0
b1111110111110111 =
b11111101 ?
b11111101 E
b11111101 P
1#
#215
0#
#220
0J
b11111111 O
b11111110 A
b11111110 G
b11111110 ?
b11111110 E
b11111110 P
b1111111011111011 "
b1111111011111011 0
b1111111011111011 =
b11111011 B
b11111011 L
b10 1
b10 5
b10 >
b10 M
1#
#225
0#
#230
1J
b11111111 A
b11111111 G
b1 1
b1 5
b1 >
b1 M
b1111101 B
b1111101 L
b1111111101111101 "
b1111111101111101 0
b1111111101111101 =
b11111111 ?
b11111111 E
b11111111 P
1#
#235
0#
#240
b1 *
b1 4
b1 <
0N
0/
0,
0+
0)
b100 7
b1111111110111110 "
b1111111110111110 0
b1111111110111110 =
b10111110 B
b10111110 L
b0 1
b0 5
b0 >
b0 M
1#
#245
0#
#250
b0 7
1%
b10 '
1!
b100 8
0#
#255
0!
12
b0 8
1#
#260
b1 7
1&
0%
0#
#265
0J
b0 O
b10 7
1.
02
b0 A
b0 G
b1 8
b1000 1
b1000 5
b1000 >
b1000 M
b0 B
b0 L
b0 *
b0 4
b0 <
0@
b0 "
b0 0
b0 =
b0 ?
b0 E
b0 P
1#
#270
b100 $
b100 (
b100 ;
b100 H
b100 K
0&
0#
#275
1-
0.
b11 7
b100 C
b100 F
b100 I
b10 8
1#
#280
b1010 $
b1010 (
b1010 ;
b1010 H
b1010 K
0#
#285
1/
1)
1,
1+
0-
b11 8
b1010 "
b1010 0
b1010 =
b1010 B
b1010 L
1#
#290
0#
#295
b11111110 O
b11111100 A
b11111100 G
b10 3
b10 6
b10 9
b10 D
b10 *
b10 4
b10 <
1N
b101 "
b101 0
b101 =
b101 B
b101 L
b111 1
b111 5
b111 >
b111 M
1#
#300
0#
#305
b1 O
0N
b1 3
b1 6
b1 9
b1 D
b10 A
b10 G
b110 1
b110 5
b110 >
b110 M
b10 B
b10 L
b1 *
b1 4
b1 <
1@
b1111111000000010 "
b1111111000000010 0
b1111111000000010 =
b11111110 ?
b11111110 E
b11111110 P
1#
#310
0#
#315
1J
b11111110 O
b11111101 A
b11111101 G
1N
b10 3
b10 6
b10 9
b10 D
b1 ?
b1 E
b1 P
b10 *
b10 4
b10 <
0@
b100000001 "
b100000001 0
b100000001 =
b1 B
b1 L
b101 1
b101 5
b101 >
b101 M
1#
#320
0#
#325
0J
b1 O
0N
b1 3
b1 6
b1 9
b1 D
b10 A
b10 G
b100 1
b100 5
b100 >
b100 M
b10000000 B
b10000000 L
b1 *
b1 4
b1 <
1@
b1111111010000000 "
b1111111010000000 0
b1111111010000000 =
b11111110 ?
b11111110 E
b11111110 P
1#
#330
0#
#335
1J
b0 O
b1 A
b1 G
b0 3
b0 6
b0 9
b0 D
b1 ?
b1 E
b1 P
b0 *
b0 4
b0 <
0@
b101000000 "
b101000000 0
b101000000 =
b1000000 B
b1000000 L
b11 1
b11 5
b11 >
b11 M
1#
#340
0#
#345
0J
b0 A
b0 G
b10 1
b10 5
b10 >
b10 M
b10100000 B
b10100000 L
b10100000 "
b10100000 0
b10100000 =
b0 ?
b0 E
b0 P
1#
#350
0#
#355
b1010000 "
b1010000 0
b1010000 =
b1010000 B
b1010000 L
b1 1
b1 5
b1 >
b1 M
1#
#360
0#
#365
0/
0,
0+
0)
b100 7
b0 1
b0 5
b0 >
b0 M
b101000 "
b101000 0
b101000 =
b101000 B
b101000 L
1#
#370
0#
#375
b0 7
1%
b1 '
1!
b100 8
0#
#380
0!
12
b0 8
1#
#385
b1 7
1&
0%
0#
#390
1.
02
b10 7
b0 "
b0 0
b0 =
b0 B
b0 L
b1000 1
b1000 5
b1000 >
b1000 M
b1 8
1#
#395
b110011 $
b110011 (
b110011 ;
b110011 H
b110011 K
0&
0#
#400
1-
0.
b11 7
b10 8
b110011 C
b110011 F
b110011 I
1#
#405
b11111101 $
b11111101 (
b11111101 ;
b11111101 H
b11111101 K
0#
#410
1J
b11100110 O
b11001101 A
b11001101 G
b10 3
b10 6
b10 9
b10 D
b10 *
b10 4
b10 <
1N
1/
1)
1,
1+
0-
b11111101 "
b11111101 0
b11111101 =
b11111101 B
b11111101 L
b11 8
1#
#415
0#
#420
1J
b1100 O
0N
b1 3
b1 6
b1 9
b1 D
b11001 A
b11001 G
b111 1
b111 5
b111 >
b111 M
b11111110 B
b11111110 L
b1 *
b1 4
b1 <
1@
b1110011011111110 "
b1110011011111110 0
b1110011011111110 =
b11100110 ?
b11100110 E
b11100110 P
1#
#425
0#
#430
1J
b11101100 O
b11011001 A
b11011001 G
1N
b10 3
b10 6
b10 9
b10 D
b1100 ?
b1100 E
b1100 P
b10 *
b10 4
b10 <
0@
b110011111111 "
b110011111111 0
b110011111111 =
b11111111 B
b11111111 L
b110 1
b110 5
b110 >
b110 M
1#
#435
0#
#440
0J
b11110110 O
b0 3
b0 6
b0 9
b0 D
b11101100 A
b11101100 G
b101 1
b101 5
b101 >
b101 M
b11 *
b11 4
b11 <
1@
b1110110011111111 "
b1110110011111111 0
b1110110011111111 =
b11101100 ?
b11101100 E
b11101100 P
1#
#445
0#
#450
b11111011 O
b11110110 A
b11110110 G
b11110110 ?
b11110110 E
b11110110 P
b1111011001111111 "
b1111011001111111 0
b1111011001111111 =
b1111111 B
b1111111 L
b100 1
b100 5
b100 >
b100 M
1#
#455
0#
#460
1J
b11111101 O
b11111011 A
b11111011 G
b11 1
b11 5
b11 >
b11 M
b111111 B
b111111 L
b1111101100111111 "
b1111101100111111 0
b1111101100111111 =
b11111011 ?
b11111011 E
b11111011 P
1#
#465
0#
#470
b11111110 O
b11111101 A
b11111101 G
b11111101 ?
b11111101 E
b11111101 P
b1111110110011111 "
b1111110110011111 0
b1111110110011111 =
b10011111 B
b10011111 L
b10 1
b10 5
b10 >
b10 M
1#
#475
0#
#480
0J
b11111111 O
b11111110 A
b11111110 G
b1 1
b1 5
b1 >
b1 M
b11001111 B
b11001111 L
b1111111011001111 "
b1111111011001111 0
b1111111011001111 =
b11111110 ?
b11111110 E
b11111110 P
1#
#485
0#
#490
1J
b11111111 A
b11111111 G
0/
0,
0+
0)
b100 7
b11111111 ?
b11111111 E
b11111111 P
b1111111101100111 "
b1111111101100111 0
b1111111101100111 =
b1100111 B
b1100111 L
b0 1
b0 5
b0 >
b0 M
1#
#495
0#
#500
b0 7
1%
b0 '
1!
b100 8
0#
#505
0!
12
b0 8
1#
#510
b1 7
1&
0%
0#
#515
0J
b0 O
b10 7
0N
1.
02
b0 A
b0 G
b1 8
b1000 1
b1000 5
b1000 >
b1000 M
b0 B
b0 L
b0 *
b0 4
b0 <
0@
b0 "
b0 0
b0 =
b0 ?
b0 E
b0 P
1#
#520
b1110 $
b1110 (
b1110 ;
b1110 H
b1110 K
0&
0#
#525
1-
0.
b11 7
b1110 C
b1110 F
b1110 I
b10 8
1#
#530
b101 $
b101 (
b101 ;
b101 H
b101 K
0#
#535
b11111001 O
b11110010 A
b11110010 G
b10 3
b10 6
b10 9
b10 D
1/
1)
1,
1+
0-
b10 *
b10 4
b10 <
1N
b11 8
b101 "
b101 0
b101 =
b101 B
b101 L
1#
#540
0#
#545
1J
b11 O
b111 A
b111 G
0N
b1 3
b1 6
b1 9
b1 D
b11111001 ?
b11111001 E
b11111001 P
b1 *
b1 4
b1 <
1@
b1111100100000010 "
b1111100100000010 0
b1111100100000010 =
b10 B
b10 L
b111 1
b111 5
b111 >
b111 M
1#
#550
0#
#555
b11111010 O
1N
b10 3
b10 6
b10 9
b10 D
b11110101 A
b11110101 G
b110 1
b110 5
b110 >
b110 M
b10000001 B
b10000001 L
b10 *
b10 4
b10 <
0@
b1110000001 "
b1110000001 0
b1110000001 =
b11 ?
b11 E
b11 P
1#
#560
0#
#565
0J
b100 O
b1000 A
b1000 G
0N
b1 3
b1 6
b1 9
b1 D
b11111010 ?
b11111010 E
b11111010 P
b1 *
b1 4
b1 <
1@
b1111101011000000 "
b1111101011000000 0
b1111101011000000 =
b11000000 B
b11000000 L
b101 1
b101 5
b101 >
b101 M
1#
#570
0#
#575
b10 O
b0 3
b0 6
b0 9
b0 D
b100 A
b100 G
b100 1
b100 5
b100 >
b100 M
b1100000 B
b1100000 L
b0 *
b0 4
b0 <
0@
b10001100000 "
b10001100000 0
b10001100000 =
b100 ?
b100 E
b100 P
1#
#580
0#
#585
b1 O
b10 A
b10 G
b10 ?
b10 E
b10 P
b1000110000 "
b1000110000 0
b1000110000 =
b110000 B
b110000 L
b11 1
b11 5
b11 >
b11 M
1#
#590
0#
#595
1J
b0 O
b1 A
b1 G
b10 1
b10 5
b10 >
b10 M
b11000 B
b11000 L
b100011000 "
b100011000 0
b100011000 =
b1 ?
b1 E
b1 P
1#
#600
0#
#605
0J
b0 A
b0 G
b0 ?
b0 E
b0 P
b10001100 "
b10001100 0
b10001100 =
b10001100 B
b10001100 L
b1 1
b1 5
b1 >
b1 M
1#
#610
0#
#615
0/
0,
0+
0)
b100 7
b0 1
b0 5
b0 >
b0 M
b1000110 "
b1000110 0
b1000110 =
b1000110 B
b1000110 L
1#
#620
0#
#625
1!
b100 8
1#
