gcd_calculator/gcd.v
module PIPO #(
    parameter size = 8)
 (
    output reg [size-1:0] data_out,
    input [size-1:0] data_in,
    input ld,
    input clk
);
always@(posedge clk)
    begin
        if(ld) data_out<=data_in;
    end
endmodule

module mux #(
    parameter size = 8
) ( output [size-1:0] out,
    input [size-1:0] A,
    input [size-1:0] B,
    input sel    
);
assign out = (sel)?B:A;    
endmodule

module comp(a,b,lt,gt,eq);
    parameter size =8;
  
    input [size-1:0] a;
    input [size-1:0] b;
    output lt;
    output gt;
    output eq;

    assign lt = a<b;
    assign gt = a>b;
    assign eq = a == b;

endmodule

module sub (x,y,out);
    parameter size = 8;
    input [size-1:0] x;
    input [size-1:0] y;
    output [size-1:0] out;

    assign out = x - y;
endmodule

module datapath(data_in, clk, lda, ldb, sel1, sel2, sel_in, lt, gt, eq, data_out);
    parameter size = 8;

    input [size-1:0] data_in;
    input lda,ldb,clk,sel1,sel2,sel_in;
    output lt, gt, eq;
    output [size-1:0] data_out;
    wire [size-1:0] bus,A,B,sub_out,X,Y;
    
    PIPO A_reg(A,bus,lda,clk);
    PIPO B_reg(B,bus,ldb,clk);
    mux  m1(X,A,B,sel1);
    mux m2(Y,A,B,sel2);
    sub s0(X,Y,sub_out);
    mux m3(bus, sub_out, data_in, sel_in);
    comp c0(A,B,lt,gt,eq);
    assign data_out = A;

endmodule

module controller(start,reset,clk,lt,eq,gt,lda,ldb,sel1,sel2,sel_in,done);

    input start,reset,clk,lt,gt,eq;
    output reg lda,ldb,sel1,sel2,sel_in,done;
    reg [3:0] state,next_state;

    parameter s0 = 3'b000, s1 = 3'b001, s2 = 3'b010, s3 = 3'b011, s4 = 3'b100;

    always@(posedge clk)
        begin
            state<=next_state;
        end

    // next state logic
    always@(state,eq,reset)
        begin
            case (state)
                s0: if(start) next_state = s1; else next_state = s0;
                s1: if(reset) next_state = s0; else next_state = s2;
                s2: if(reset) next_state = s0; else next_state = s3;
                s3: if(reset) next_state = s0; else begin if(eq) next_state = s4; else next_state = s3; end
                s4: if(reset) next_state = s0; else next_state = s4;
                default: next_state = s0;
            endcase
        end
    
    // output logic
    always@(state,lt,gt,eq)
        begin
            case (state)
                s0:  begin  lda = 0; ldb = 0; sel1=0; sel2=0; sel_in=0; done = 0;end
                s1:  begin  lda = 1; ldb = 0; sel_in = 1;end
                s2:  begin  lda = 0; ldb = 1; sel_in = 1;end
                s3:
                begin
                    if(lt) begin sel1 = 1; sel2 = 0; sel_in = 0; lda = 0; ldb = 1; end
                    else if(gt) begin sel1 = 0; sel2 = 1; sel_in = 0; lda = 1; ldb = 0; end
                    else begin lda = 0; ldb = 0; end    
                end
                s4: begin done = 1; lda = 0; ldb = 0; end
            endcase
        end
endmodule

module gcd(start, reset, clk, data_in, data_out, done);
    
    parameter size = 8;
    input start, reset, clk;
    input [size-1:0] data_in;
    output [size-1:0] data_out;
    output done;
    
    wire lda, ldb, sel1,sel2,sel_in,lt,gt,eq;

    datapath #(.size(size)) d0 (data_in, clk, lda, ldb, sel1, sel2, sel_in, lt, gt, eq, data_out); 
    controller c0 (start, reset, clk, lt, eq, gt, lda, ldb, sel1,sel2, sel_in, done);

endmodule

gcd_calculator/gcd_tb.v
`include "gcd.v"
`timescale 1ns/1ps

module tb_gcd;
parameter SIZE = 8;
parameter tclk = 10;
reg start, reset, clk;
reg [SIZE-1:0] data_in;
wire [SIZE-1:0] data_out;
wire done;

integer n = 5;

gcd g0(start,reset,clk,data_in,data_out,done);

task generate_stimulus();
begin
    start <= 1'b0; reset <=1'b1; clk <= 1'b0;
    #(tclk) reset<=1'b0; start<=1'b1;
    #(tclk) start<=1'b0; data_in<=$random;
    #(tclk) data_in<=$random;
end
endtask

initial
begin
    $dumpfile("tb_gcd.vcd");
    $dumpvars(0,tb_gcd);
end

// generating the clock.
always #(tclk/2) clk = ~clk;

// Generating input stimulus
initial
begin
    n = n-1;
    generate_stimulus();
end

always@(posedge done)
begin
    if(n == 0) $finish;
    n = n-1;
    generate_stimulus();
end



initial
# 1000 $finish;

// Monitoring signals
initial
begin
    $monitor("time = %t, A = %d, B = %d, done=%b",$time, g0.d0.A, g0.d0.B,done);
end
endmodule

gcd_calculator/tb_gcd.vcd
$date
	Mon Oct  7 01:07:22 2024
$end
$version
	Icarus Verilog
$end
$timescale
	1ps
$end
$scope module tb_gcd $end
$var wire 1 ! done $end
$var wire 8 " data_out [7:0] $end
$var reg 1 # clk $end
$var reg 8 $ data_in [7:0] $end
$var reg 1 % reset $end
$var reg 1 & start $end
$var integer 32 ' n [31:0] $end
$scope module g0 $end
$var wire 1 # clk $end
$var wire 8 ( data_in [7:0] $end
$var wire 1 % reset $end
$var wire 1 & start $end
$var wire 1 ) sel_in $end
$var wire 1 * sel2 $end
$var wire 1 + sel1 $end
$var wire 1 , lt $end
$var wire 1 - ldb $end
$var wire 1 . lda $end
$var wire 1 / gt $end
$var wire 1 0 eq $end
$var wire 1 ! done $end
$var wire 8 1 data_out [7:0] $end
$scope module c0 $end
$var wire 1 # clk $end
$var wire 1 % reset $end
$var wire 1 & start $end
$var wire 1 , lt $end
$var wire 1 / gt $end
$var wire 1 0 eq $end
$var reg 1 ! done $end
$var reg 1 . lda $end
$var reg 1 - ldb $end
$var reg 4 2 next_state [3:0] $end
$var reg 1 + sel1 $end
$var reg 1 * sel2 $end
$var reg 1 ) sel_in $end
$var reg 4 3 state [3:0] $end
$upscope $end
$scope module d0 $end
$var wire 1 # clk $end
$var wire 8 4 data_in [7:0] $end
$var wire 8 5 data_out [7:0] $end
$var wire 1 . lda $end
$var wire 1 - ldb $end
$var wire 1 + sel1 $end
$var wire 1 * sel2 $end
$var wire 1 ) sel_in $end
$var wire 8 6 sub_out [7:0] $end
$var wire 1 , lt $end
$var wire 1 / gt $end
$var wire 1 0 eq $end
$var wire 8 7 bus [7:0] $end
$var wire 8 8 Y [7:0] $end
$var wire 8 9 X [7:0] $end
$var wire 8 : B [7:0] $end
$var wire 8 ; A [7:0] $end
$scope module A_reg $end
$var wire 1 # clk $end
$var wire 1 . ld $end
$var wire 8 < data_in [7:0] $end
$var reg 8 = data_out [7:0] $end
$upscope $end
$scope module B_reg $end
$var wire 1 # clk $end
$var wire 1 - ld $end
$var wire 8 > data_in [7:0] $end
$var reg 8 ? data_out [7:0] $end
$upscope $end
$scope module c0 $end
$var wire 8 @ a [7:0] $end
$var wire 8 A b [7:0] $end
$var wire 1 , lt $end
$var wire 1 / gt $end
$var wire 1 0 eq $end
$upscope $end
$scope module m1 $end
$var wire 8 B A [7:0] $end
$var wire 8 C B [7:0] $end
$var wire 1 + sel $end
$var wire 8 D out [7:0] $end
$upscope $end
$scope module m2 $end
$var wire 8 E A [7:0] $end
$var wire 8 F B [7:0] $end
$var wire 1 * sel $end
$var wire 8 G out [7:0] $end
$upscope $end
$scope module m3 $end
$var wire 8 H B [7:0] $end
$var wire 1 ) sel $end
$var wire 8 I out [7:0] $end
$var wire 8 J A [7:0] $end
$upscope $end
$scope module s0 $end
$var wire 8 K x [7:0] $end
$var wire 8 L y [7:0] $end
$var wire 8 M out [7:0] $end
$upscope $end
$upscope $end
$upscope $end
$scope task generate_stimulus $end
$upscope $end
$upscope $end
$enddefinitions $end
#0
$dumpvars
bx M
bx L
bx K
bx J
bx I
bx H
bx G
bx F
bx E
bx D
bx C
bx B
bx A
bx @
bx ?
bx >
bx =
bx <
bx ;
bx :
bx 9
bx 8
bx 7
bx 6
bx 5
bx 4
bx 3
b0 2
bx 1
x0
x/
x.
x-
x,
x+
x*
x)
bx (
b100 '
0&
1%
bx $
0#
bx "
x!
$end
#5000
0!
0)
0*
0+
0-
0.
b0 3
1#
#10000
b1 2
1&
0%
0#
#15000
1)
1.
b10 2
b1 3
1#
#20000
b100100 7
b100100 <
b100100 >
b100100 I
b100100 $
b100100 (
b100100 4
b100100 H
0&
0#
#25000
b0 6
b0 J
b0 M
b100100 9
b100100 D
b100100 K
b100100 8
b100100 G
b100100 L
1-
0.
b11 2
b100100 "
b100100 1
b100100 5
b100100 ;
b100100 =
b100100 @
b100100 B
b100100 E
b10 3
1#
#30000
b10000001 7
b10000001 <
b10000001 >
b10000001 I
b10000001 $
b10000001 (
b10000001 4
b10000001 H
0#
#35000
b1011101 7
b1011101 <
b1011101 >
b1011101 I
b1011101 6
b1011101 J
b1011101 M
b10000001 9
b10000001 D
b10000001 K
0)
1+
b11 3
1,
0/
00
b10000001 :
b10000001 ?
b10000001 A
b10000001 C
b10000001 F
1#
#40000
0#
#45000
b111001 7
b111001 <
b111001 >
b111001 I
b111001 6
b111001 J
b111001 M
b1011101 9
b1011101 D
b1011101 K
b1011101 :
b1011101 ?
b1011101 A
b1011101 C
b1011101 F
1#
#50000
0#
#55000
b10101 7
b10101 <
b10101 >
b10101 I
b10101 6
b10101 J
b10101 M
b111001 9
b111001 D
b111001 K
b111001 :
b111001 ?
b111001 A
b111001 C
b111001 F
1#
#60000
0#
#65000
b10101 8
b10101 G
b10101 L
b1111 7
b1111 <
b1111 >
b1111 I
0-
1.
1*
0+
b1111 6
b1111 J
b1111 M
b100100 9
b100100 D
b100100 K
0,
1/
b10101 :
b10101 ?
b10101 A
b10101 C
b10101 F
1#
#70000
0#
#75000
b1111 8
b1111 G
b1111 L
b110 7
b110 <
b110 >
b110 I
1-
0.
0*
1+
b110 6
b110 J
b110 M
b10101 9
b10101 D
b10101 K
1,
0/
b1111 "
b1111 1
b1111 5
b1111 ;
b1111 =
b1111 @
b1111 B
b1111 E
1#
#80000
0#
#85000
b110 8
b110 G
b110 L
b1001 7
b1001 <
b1001 >
b1001 I
0-
1.
1*
0+
b1001 6
b1001 J
b1001 M
b1111 9
b1111 D
b1111 K
0,
1/
b110 :
b110 ?
b110 A
b110 C
b110 F
1#
#90000
0#
#95000
b11 7
b11 <
b11 >
b11 I
b11 6
b11 J
b11 M
b1001 9
b1001 D
b1001 K
b1001 "
b1001 1
b1001 5
b1001 ;
b1001 =
b1001 @
b1001 B
b1001 E
1#
#100000
0#
#105000
b11 8
b11 G
b11 L
b11 7
b11 <
b11 >
b11 I
1-
0.
0*
1+
b11 6
b11 J
b11 M
b110 9
b110 D
b110 K
1,
0/
b11 "
b11 1
b11 5
b11 ;
b11 =
b11 @
b11 B
b11 E
1#
#110000
0#
#115000
b0 7
b0 <
b0 >
b0 I
0-
b100 2
b0 6
b0 J
b0 M
b11 9
b11 D
b11 K
0,
10
b11 :
b11 ?
b11 A
b11 C
b11 F
1#
#120000
0#
#125000
b0 2
1%
b11 '
1!
b100 3
0#
#130000
0!
0+
b0 3
1#
#135000
b1 2
1&
0%
0#
#140000
b10000001 7
b10000001 <
b10000001 >
b10000001 I
1)
1.
b10 2
b1 3
1#
#145000
b1001 7
b1001 <
b1001 >
b1001 I
b1001 $
b1001 (
b1001 4
b1001 H
0&
0#
#150000
1-
0.
b11 2
b1001 9
b1001 D
b1001 K
b0 6
b0 J
b0 M
b1001 8
b1001 G
b1001 L
b10 3
1/
00
b1001 "
b1001 1
b1001 5
b1001 ;
b1001 =
b1001 @
b1001 B
b1001 E
1#
#155000
b1100011 7
b1100011 <
b1100011 >
b1100011 I
b1100011 $
b1100011 (
b1100011 4
b1100011 H
0#
#160000
b1011010 7
b1011010 <
b1011010 >
b1011010 I
b1011010 6
b1011010 J
b1011010 M
b1100011 9
b1100011 D
b1100011 K
0)
1+
1,
0/
b1100011 :
b1100011 ?
b1100011 A
b1100011 C
b1100011 F
b11 3
1#
#165000
0#
#170000
b1010001 7
b1010001 <
b1010001 >
b1010001 I
b1010001 6
b1010001 J
b1010001 M
b1011010 9
b1011010 D
b1011010 K
b1011010 :
b1011010 ?
b1011010 A
b1011010 C
b1011010 F
1#
#175000
0#
#180000
b1001000 7
b1001000 <
b1001000 >
b1001000 I
b1001000 6
b1001000 J
b1001000 M
b1010001 9
b1010001 D
b1010001 K
b1010001 :
b1010001 ?
b1010001 A
b1010001 C
b1010001 F
1#
#185000
0#
#190000
b111111 7
b111111 <
b111111 >
b111111 I
b111111 6
b111111 J
b111111 M
b1001000 9
b1001000 D
b1001000 K
b1001000 :
b1001000 ?
b1001000 A
b1001000 C
b1001000 F
1#
#195000
0#
#200000
b110110 7
b110110 <
b110110 >
b110110 I
b110110 6
b110110 J
b110110 M
b111111 9
b111111 D
b111111 K
b111111 :
b111111 ?
b111111 A
b111111 C
b111111 F
1#
#205000
0#
#210000
b101101 7
b101101 <
b101101 >
b101101 I
b101101 6
b101101 J
b101101 M
b110110 9
b110110 D
b110110 K
b110110 :
b110110 ?
b110110 A
b110110 C
b110110 F
1#
#215000
0#
#220000
b100100 7
b100100 <
b100100 >
b100100 I
b100100 6
b100100 J
b100100 M
b101101 9
b101101 D
b101101 K
b101101 :
b101101 ?
b101101 A
b101101 C
b101101 F
1#
#225000
0#
#230000
b11011 7
b11011 <
b11011 >
b11011 I
b11011 6
b11011 J
b11011 M
b100100 9
b100100 D
b100100 K
b100100 :
b100100 ?
b100100 A
b100100 C
b100100 F
1#
#235000
0#
#240000
b10010 7
b10010 <
b10010 >
b10010 I
b10010 6
b10010 J
b10010 M
b11011 9
b11011 D
b11011 K
b11011 :
b11011 ?
b11011 A
b11011 C
b11011 F
1#
#245000
0#
#250000
b1001 7
b1001 <
b1001 >
b1001 I
b1001 6
b1001 J
b1001 M
b10010 9
b10010 D
b10010 K
b10010 :
b10010 ?
b10010 A
b10010 C
b10010 F
1#
#255000
0#
#260000
b0 7
b0 <
b0 >
b0 I
0-
b100 2
b0 6
b0 J
b0 M
b1001 9
b1001 D
b1001 K
0,
10
b1001 :
b1001 ?
b1001 A
b1001 C
b1001 F
1#
#265000
0#
#270000
b0 2
1%
b10 '
1!
b100 3
0#
#275000
0!
0+
b0 3
1#
#280000
b1 2
1&
0%
0#
#285000
b1100011 7
b1100011 <
b1100011 >
b1100011 I
1)
1.
b10 2
b1 3
1#
#290000
b1101 7
b1101 <
b1101 >
b1101 I
b1101 $
b1101 (
b1101 4
b1101 H
0&
0#
#295000
b1101 9
b1101 D
b1101 K
b0 6
b0 J
b0 M
b1101 8
b1101 G
b1101 L
1-
0.
b11 2
1/
00
b1101 "
b1101 1
b1101 5
b1101 ;
b1101 =
b1101 @
b1101 B
b1101 E
b10 3
1#
#300000
b10001101 7
b10001101 <
b10001101 >
b10001101 I
b10001101 $
b10001101 (
b10001101 4
b10001101 H
0#
#305000
b10000000 7
b10000000 <
b10000000 >
b10000000 I
b10000000 6
b10000000 J
b10000000 M
b10001101 9
b10001101 D
b10001101 K
0)
1+
b11 3
1,
0/
b10001101 :
b10001101 ?
b10001101 A
b10001101 C
b10001101 F
1#
#310000
0#
#315000
b1110011 7
b1110011 <
b1110011 >
b1110011 I
b1110011 6
b1110011 J
b1110011 M
b10000000 9
b10000000 D
b10000000 K
b10000000 :
b10000000 ?
b10000000 A
b10000000 C
b10000000 F
1#
#320000
0#
#325000
b1100110 7
b1100110 <
b1100110 >
b1100110 I
b1100110 6
b1100110 J
b1100110 M
b1110011 9
b1110011 D
b1110011 K
b1110011 :
b1110011 ?
b1110011 A
b1110011 C
b1110011 F
1#
#330000
0#
#335000
b1011001 7
b1011001 <
b1011001 >
b1011001 I
b1011001 6
b1011001 J
b1011001 M
b1100110 9
b1100110 D
b1100110 K
b1100110 :
b1100110 ?
b1100110 A
b1100110 C
b1100110 F
1#
#340000
0#
#345000
b1001100 7
b1001100 <
b1001100 >
b1001100 I
b1001100 6
b1001100 J
b1001100 M
b1011001 9
b1011001 D
b1011001 K
b1011001 :
b1011001 ?
b1011001 A
b1011001 C
b1011001 F
1#
#350000
0#
#355000
b111111 7
b111111 <
b111111 >
b111111 I
b111111 6
b111111 J
b111111 M
b1001100 9
b1001100 D
b1001100 K
b1001100 :
b1001100 ?
b1001100 A
b1001100 C
b1001100 F
1#
#360000
0#
#365000
b110010 7
b110010 <
b110010 >
b110010 I
b110010 6
b110010 J
b110010 M
b111111 9
b111111 D
b111111 K
b111111 :
b111111 ?
b111111 A
b111111 C
b111111 F
1#
#370000
0#
#375000
b100101 7
b100101 <
b100101 >
b100101 I
b100101 6
b100101 J
b100101 M
b110010 9
b110010 D
b110010 K
b110010 :
b110010 ?
b110010 A
b110010 C
b110010 F
1#
#380000
0#
#385000
b11000 7
b11000 <
b11000 >
b11000 I
b11000 6
b11000 J
b11000 M
b100101 9
b100101 D
b100101 K
b100101 :
b100101 ?
b100101 A
b100101 C
b100101 F
1#
#390000
0#
#395000
b1011 7
b1011 <
b1011 >
b1011 I
b1011 6
b1011 J
b1011 M
b11000 9
b11000 D
b11000 K
b11000 :
b11000 ?
b11000 A
b11000 C
b11000 F
1#
#400000
0#
#405000
b1011 8
b1011 G
b1011 L
b10 7
b10 <
b10 >
b10 I
0-
1.
1*
0+
b10 6
b10 J
b10 M
b1101 9
b1101 D
b1101 K
0,
1/
b1011 :
b1011 ?
b1011 A
b1011 C
b1011 F
1#
#410000
0#
#415000
b10 8
b10 G
b10 L
b1001 7
b1001 <
b1001 >
b1001 I
1-
0.
0*
1+
b1001 6
b1001 J
b1001 M
b1011 9
b1011 D
b1011 K
1,
0/
b10 "
b10 1
b10 5
b10 ;
b10 =
b10 @
b10 B
b10 E
1#
#420000
0#
#425000
b111 7
b111 <
b111 >
b111 I
b111 6
b111 J
b111 M
b1001 9
b1001 D
b1001 K
b1001 :
b1001 ?
b1001 A
b1001 C
b1001 F
1#
#430000
0#
#435000
b101 7
b101 <
b101 >
b101 I
b101 6
b101 J
b101 M
b111 9
b111 D
b111 K
b111 :
b111 ?
b111 A
b111 C
b111 F
1#
#440000
0#
#445000
b11 7
b11 <
b11 >
b11 I
b11 6
b11 J
b11 M
b101 9
b101 D
b101 K
b101 :
b101 ?
b101 A
b101 C
b101 F
1#
#450000
0#
#455000
b1 7
b1 <
b1 >
b1 I
b1 6
b1 J
b1 M
b11 9
b11 D
b11 K
b11 :
b11 ?
b11 A
b11 C
b11 F
1#
#460000
0#
#465000
b1 8
b1 G
b1 L
b1 7
b1 <
b1 >
b1 I
0-
1.
1*
0+
b1 6
b1 J
b1 M
b10 9
b10 D
b10 K
0,
1/
b1 :
b1 ?
b1 A
b1 C
b1 F
1#
#470000
0#
#475000
b0 7
b0 <
b0 >
b0 I
0.
b100 2
b0 6
b0 J
b0 M
b1 9
b1 D
b1 K
0/
10
b1 "
b1 1
b1 5
b1 ;
b1 =
b1 @
b1 B
b1 E
1#
#480000
0#
#485000
b0 2
1%
b1 '
1!
b100 3
0#
#490000
0!
0*
b0 3
1#
#495000
b1 2
1&
0%
0#
#500000
b10001101 7
b10001101 <
b10001101 >
b10001101 I
1)
1.
b10 2
b1 3
1#
#505000
b1100101 7
b1100101 <
b1100101 >
b1100101 I
b1100101 $
b1100101 (
b1100101 4
b1100101 H
0&
0#
#510000
b1100101 9
b1100101 D
b1100101 K
b0 6
b0 J
b0 M
b1100101 8
b1100101 G
b1100101 L
1-
0.
b11 2
1/
00
b1100101 "
b1100101 1
b1100101 5
b1100101 ;
b1100101 =
b1100101 @
b1100101 B
b1100101 E
b10 3
1#
#515000
b10010 7
b10010 <
b10010 >
b10010 I
b10010 $
b10010 (
b10010 4
b10010 H
0#
#520000
b1010011 7
b1010011 <
b1010011 >
b1010011 I
b1010011 6
b1010011 J
b1010011 M
b10010 8
b10010 G
b10010 L
0-
1.
0)
1*
b11 3
b10010 :
b10010 ?
b10010 A
b10010 C
b10010 F
1#
#525000
0#
#530000
b1000001 7
b1000001 <
b1000001 >
b1000001 I
b1000001 6
b1000001 J
b1000001 M
b1010011 9
b1010011 D
b1010011 K
b1010011 "
b1010011 1
b1010011 5
b1010011 ;
b1010011 =
b1010011 @
b1010011 B
b1010011 E
1#
#535000
0#
#540000
b101111 7
b101111 <
b101111 >
b101111 I
b101111 6
b101111 J
b101111 M
b1000001 9
b1000001 D
b1000001 K
b1000001 "
b1000001 1
b1000001 5
b1000001 ;
b1000001 =
b1000001 @
b1000001 B
b1000001 E
1#
#545000
0#
#550000
b11101 7
b11101 <
b11101 >
b11101 I
b11101 6
b11101 J
b11101 M
b101111 9
b101111 D
b101111 K
b101111 "
b101111 1
b101111 5
b101111 ;
b101111 =
b101111 @
b101111 B
b101111 E
1#
#555000
0#
#560000
b1011 7
b1011 <
b1011 >
b1011 I
b1011 6
b1011 J
b1011 M
b11101 9
b11101 D
b11101 K
b11101 "
b11101 1
b11101 5
b11101 ;
b11101 =
b11101 @
b11101 B
b11101 E
1#
#565000
0#
#570000
b1011 8
b1011 G
b1011 L
b111 7
b111 <
b111 >
b111 I
1-
0.
0*
1+
b111 6
b111 J
b111 M
b10010 9
b10010 D
b10010 K
1,
0/
b1011 "
b1011 1
b1011 5
b1011 ;
b1011 =
b1011 @
b1011 B
b1011 E
1#
#575000
0#
#580000
b111 8
b111 G
b111 L
b100 7
b100 <
b100 >
b100 I
0-
1.
1*
0+
b100 6
b100 J
b100 M
b1011 9
b1011 D
b1011 K
0,
1/
b111 :
b111 ?
b111 A
b111 C
b111 F
1#
#585000
0#
#590000
b100 8
b100 G
b100 L
b11 7
b11 <
b11 >
b11 I
1-
0.
0*
1+
b11 6
b11 J
b11 M
b111 9
b111 D
b111 K
1,
0/
b100 "
b100 1
b100 5
b100 ;
b100 =
b100 @
b100 B
b100 E
1#
#595000
0#
#600000
b11 8
b11 G
b11 L
b1 7
b1 <
b1 >
b1 I
0-
1.
1*
0+
b1 6
b1 J
b1 M
b100 9
b100 D
b100 K
0,
1/
b11 :
b11 ?
b11 A
b11 C
b11 F
1#
#605000
0#
#610000
b1 8
b1 G
b1 L
b10 7
b10 <
b10 >
b10 I
1-
0.
0*
1+
b10 6
b10 J
b10 M
b11 9
b11 D
b11 K
1,
0/
b1 "
b1 1
b1 5
b1 ;
b1 =
b1 @
b1 B
b1 E
1#
#615000
0#
#620000
b1 7
b1 <
b1 >
b1 I
b1 6
b1 J
b1 M
b10 9
b10 D
b10 K
b10 :
b10 ?
b10 A
b10 C
b10 F
1#
#625000
0#
#630000
b0 7
b0 <
b0 >
b0 I
0-
b100 2
b0 6
b0 J
b0 M
b1 9
b1 D
b1 K
0,
10
b1 :
b1 ?
b1 A
b1 C
b1 F
1#
#635000
0#
#640000
b0 2
1%
b0 '
1!
b100 3
0#
#645000
0!
0+
b0 3
1#
#650000
b1 2
1&
0%
0#
#655000
b10010 7
b10010 <
b10010 >
b10010 I
1)
1.
b10 2
b1 3
1#
#660000
b1 7
b1 <
b1 >
b1 I
b1 $
b1 (
b1 4
b1 H
0&
0#
#665000
1-
0.
b11 2
b10 3
1#
#670000
b1101 7
b1101 <
b1101 >
b1101 I
b1101 $
b1101 (
b1101 4
b1101 H
0#
#675000
b1100 7
b1100 <
b1100 >
b1100 I
b1100 6
b1100 J
b1100 M
b1101 9
b1101 D
b1101 K
0)
1+
b11 3
1,
00
b1101 :
b1101 ?
b1101 A
b1101 C
b1101 F
1#
#680000
0#
#685000
b1011 7
b1011 <
b1011 >
b1011 I
b1011 6
b1011 J
b1011 M
b1100 9
b1100 D
b1100 K
b1100 :
b1100 ?
b1100 A
b1100 C
b1100 F
1#
#690000
0#
#695000
b1010 7
b1010 <
b1010 >
b1010 I
b1010 6
b1010 J
b1010 M
b1011 9
b1011 D
b1011 K
b1011 :
b1011 ?
b1011 A
b1011 C
b1011 F
1#
#700000
0#
#705000
b1001 7
b1001 <
b1001 >
b1001 I
b1001 6
b1001 J
b1001 M
b1010 9
b1010 D
b1010 K
b1010 :
b1010 ?
b1010 A
b1010 C
b1010 F
1#
#710000
0#
#715000
b1000 7
b1000 <
b1000 >
b1000 I
b1000 6
b1000 J
b1000 M
b1001 9
b1001 D
b1001 K
b1001 :
b1001 ?
b1001 A
b1001 C
b1001 F
1#
#720000
0#
#725000
b111 7
b111 <
b111 >
b111 I
b111 6
b111 J
b111 M
b1000 9
b1000 D
b1000 K
b1000 :
b1000 ?
b1000 A
b1000 C
b1000 F
1#
#730000
0#
#735000
b110 7
b110 <
b110 >
b110 I
b110 6
b110 J
b110 M
b111 9
b111 D
b111 K
b111 :
b111 ?
b111 A
b111 C
b111 F
1#
#740000
0#
#745000
b101 7
b101 <
b101 >
b101 I
b101 6
b101 J
b101 M
b110 9
b110 D
b110 K
b110 :
b110 ?
b110 A
b110 C
b110 F
1#
#750000
0#
#755000
b100 7
b100 <
b100 >
b100 I
b100 6
b100 J
b100 M
b101 9
b101 D
b101 K
b101 :
b101 ?
b101 A
b101 C
b101 F
1#
#760000
0#
#765000
b11 7
b11 <
b11 >
b11 I
b11 6
b11 J
b11 M
b100 9
b100 D
b100 K
b100 :
b100 ?
b100 A
b100 C
b100 F
1#
#770000
0#
#775000
b10 7
b10 <
b10 >
b10 I
b10 6
b10 J
b10 M
b11 9
b11 D
b11 K
b11 :
b11 ?
b11 A
b11 C
b11 F
1#
#780000
0#
#785000
b1 7
b1 <
b1 >
b1 I
b1 6
b1 J
b1 M
b10 9
b10 D
b10 K
b10 :
b10 ?
b10 A
b10 C
b10 F
1#
#790000
0#
#795000
b0 7
b0 <
b0 >
b0 I
0-
b100 2
b0 6
b0 J
b0 M
b1 9
b1 D
b1 K
0,
10
b1 :
b1 ?
b1 A
b1 C
b1 F
1#
#800000
0#
#805000
1!
b100 3
1#
